{
  "data": {
    "article": {},
    "attachments": {},
    "author_id": "1659962043460354050",
    "conversation_id": "1969776820930142468",
    "created_at": "2025-09-21T14:52:45.000Z",
    "edit_controls": {
      "editable_until": "2025-09-21T15:52:45.000Z",
      "edits_remaining": 5,
      "is_edit_eligible": true
    },
    "edit_history_tweet_ids": [
      "1969776820930142468"
    ],
    "entities": {
      "urls": [
        {
          "display_url": "x.com/Longlinlon/sta…",
          "end": 75,
          "expanded_url": "https://twitter.com/Longlinlon/status/1969713523191353616",
          "start": 52,
          "url": "https://t.co/LuPTtnoVxJ"
        }
      ]
    },
    "geo": {},
    "id": "1969776820930142468",
    "lang": "zh",
    "note_tweet": {
      "entities": {}
    },
    "possibly_sensitive": false,
    "public_metrics": {
      "bookmark_count": 0,
      "impression_count": 0,
      "like_count": 0,
      "quote_count": 0,
      "reply_count": 0,
      "retweet_count": 0
    },
    "referenced_tweets": [
      {
        "id": "1969713523191353616",
        "type": "quoted"
      }
    ],
    "reply_settings": "everyone",
    "text": "看了这个ppt我气得浑身发抖，大热天的冷汗直流\n我们overdose亚文化呢?难道就不把od当人了?😡 https://t.co/LuPTtnoVxJ"
  },
  "includes": {
    "media": [
      {
        "height": 1733,
        "media_key": "3_1969713514731515904",
        "public_metrics": {},
        "type": "photo",
        "url": "https://pbs.twimg.com/media/G1XUAXLbsAAye3Z.jpg",
        "width": 1402
      }
    ],
    "tweets": [
      {
        "article": {},
        "attachments": {},
        "author_id": "1659962043460354050",
        "conversation_id": "1969776820930142468",
        "created_at": "2025-09-21T14:52:45.000Z",
        "edit_controls": {
          "editable_until": "2025-09-21T15:52:45.000Z",
          "edits_remaining": 5,
          "is_edit_eligible": true
        },
        "edit_history_tweet_ids": [
          "1969776820930142468"
        ],
        "entities": {
          "urls": [
            {
              "display_url": "x.com/Longlinlon/sta…",
              "end": 75,
              "expanded_url": "https://twitter.com/Longlinlon/status/1969713523191353616",
              "start": 52,
              "url": "https://t.co/LuPTtnoVxJ"
            }
          ]
        },
        "geo": {},
        "id": "1969776820930142468",
        "lang": "zh",
        "note_tweet": {
          "entities": {}
        },
        "possibly_sensitive": false,
        "public_metrics": {
          "bookmark_count": 0,
          "impression_count": 0,
          "like_count": 0,
          "quote_count": 0,
          "reply_count": 0,
          "retweet_count": 0
        },
        "referenced_tweets": [
          {
            "id": "1969713523191353616",
            "type": "quoted"
          }
        ],
        "reply_settings": "everyone",
        "text": "看了这个ppt我气得浑身发抖，大热天的冷汗直流\n我们overdose亚文化呢?难道就不把od当人了?😡 https://t.co/LuPTtnoVxJ"
      },
      {
        "article": {},
        "attachments": {
          "media_keys": [
            "3_1969713514731515904"
          ]
        },
        "author_id": "1596416860752207872",
        "conversation_id": "1969713523191353616",
        "created_at": "2025-09-21T10:41:14.000Z",
        "edit_controls": {
          "editable_until": "2025-09-21T11:41:14.000Z",
          "edits_remaining": 5,
          "is_edit_eligible": true
        },
        "edit_history_tweet_ids": [
          "1969713523191353616"
        ],
        "entities": {
          "urls": [
            {
              "display_url": "pic.x.com/Khm6qspol0",
              "end": 23,
              "expanded_url": "https://x.com/Longlinlon/status/1969713523191353616/photo/1",
              "media_key": "3_1969713514731515904",
              "start": 0,
              "url": "https://t.co/Khm6qspol0"
            }
          ]
        },
        "geo": {},
        "id": "1969713523191353616",
        "lang": "zxx",
        "note_tweet": {
          "entities": {}
        },
        "possibly_sensitive": false,
        "public_metrics": {
          "bookmark_count": 0,
          "impression_count": 189,
          "like_count": 7,
          "quote_count": 1,
          "reply_count": 1,
          "retweet_count": 0
        },
        "reply_settings": "everyone",
        "text": "https://t.co/Khm6qspol0"
      }
    ],
    "users": [
      {
        "created_at": "2023-05-20T16:39:35.000Z",
        "description": "07丨上海丨退役OIer丨虚无主义者丨\n非必要不键政🥺丨\nSay Know to Drugs 💊丨\n会发各种东西丨欢迎任何人🌈丨互fo🉑🥰丨如果没回fo的话，请私信哦",
        "entities": {
          "url": {
            "urls": [
              {
                "display_url": "github.com/SalviaSWC",
                "end": 23,
                "expanded_url": "https://github.com/SalviaSWC",
                "start": 0,
                "url": "https://t.co/NJRjXJi1ON"
              }
            ]
          }
        },
        "id": "1659962043460354050",
        "name": "鼠尾草～🌿",
        "profile_image_url": "https://pbs.twimg.com/profile_images/1886008586339282944/fBJFdCp0_normal.jpg",
        "protected": false,
        "public_metrics": {
          "followers_count": 1251,
          "following_count": 482,
          "like_count": 7305,
          "listed_count": 5,
          "media_count": 106,
          "tweet_count": 2547
        },
        "url": "https://t.co/NJRjXJi1ON",
        "username": "SalviaSWC",
        "verified": false
      },
      {
        "created_at": "2022-11-26T08:13:47.000Z",
        "description": "满庭芳🏳️‍⚧️",
        "id": "1596416860752207872",
        "location": "崆",
        "name": "艾达是病患和园丁的亲妈-Wiggin",
        "profile_image_url": "https://pbs.twimg.com/profile_images/1887071896212242432/STqUUbjV_normal.jpg",
        "protected": false,
        "public_metrics": {
          "followers_count": 1930,
          "following_count": 2516,
          "like_count": 215318,
          "listed_count": 10,
          "media_count": 1309,
          "tweet_count": 14339
        },
        "username": "Longlinlon",
        "verified": false
      }
    ]
  }
}