{
  "data": {
    "article": {},
    "attachments": {},
    "author_id": "1659962043460354050",
    "conversation_id": "1975564685471850677",
    "created_at": "2025-10-08T10:52:42.000Z",
    "edit_controls": {
      "editable_until": "2025-10-08T11:52:42.000Z",
      "edits_remaining": 5,
      "is_edit_eligible": false
    },
    "edit_history_tweet_ids": [
      "1975877002608701817"
    ],
    "entities": {
      "mentions": [
        {
          "end": 13,
          "id": "622036546",
          "start": 0,
          "username": "overdose_six"
        }
      ]
    },
    "geo": {},
    "id": "1975877002608701817",
    "in_reply_to_user_id": "622036546",
    "lang": "zh",
    "note_tweet": {
      "entities": {}
    },
    "possibly_sensitive": false,
    "public_metrics": {
      "bookmark_count": 0,
      "impression_count": 0,
      "like_count": 0,
      "quote_count": 0,
      "reply_count": 0,
      "retweet_count": 0
    },
    "referenced_tweets": [
      {
        "id": "1975867821893812414",
        "type": "replied_to"
      }
    ],
    "reply_settings": "everyone",
    "text": "@overdose_six 这样阿"
  },
  "includes": {
    "media": [
      {
        "height": 2048,
        "media_key": "3_1975867818555084800",
        "public_metrics": {},
        "type": "photo",
        "url": "https://pbs.twimg.com/media/G2uxT_gaEAAwBFM.jpg",
        "width": 969
      }
    ],
    "tweets": [
      {
        "article": {},
        "attachments": {},
        "author_id": "1659962043460354050",
        "conversation_id": "1975564685471850677",
        "created_at": "2025-10-08T10:52:42.000Z",
        "edit_controls": {
          "editable_until": "2025-10-08T11:52:42.000Z",
          "edits_remaining": 5,
          "is_edit_eligible": false
        },
        "edit_history_tweet_ids": [
          "1975877002608701817"
        ],
        "entities": {
          "mentions": [
            {
              "end": 13,
              "id": "622036546",
              "start": 0,
              "username": "overdose_six"
            }
          ]
        },
        "geo": {},
        "id": "1975877002608701817",
        "in_reply_to_user_id": "622036546",
        "lang": "zh",
        "note_tweet": {
          "entities": {}
        },
        "possibly_sensitive": false,
        "public_metrics": {
          "bookmark_count": 0,
          "impression_count": 0,
          "like_count": 0,
          "quote_count": 0,
          "reply_count": 0,
          "retweet_count": 0
        },
        "referenced_tweets": [
          {
            "id": "1975867821893812414",
            "type": "replied_to"
          }
        ],
        "reply_settings": "everyone",
        "text": "@overdose_six 这样阿"
      },
      {
        "article": {},
        "attachments": {
          "media_keys": [
            "3_1975867818555084800"
          ]
        },
        "author_id": "622036546",
        "conversation_id": "1975564685471850677",
        "created_at": "2025-10-08T10:16:13.000Z",
        "edit_controls": {
          "editable_until": "2025-10-08T11:16:13.000Z",
          "edits_remaining": 5,
          "is_edit_eligible": false
        },
        "edit_history_tweet_ids": [
          "1975867821893812414"
        ],
        "entities": {
          "mentions": [
            {
              "end": 10,
              "id": "1659962043460354050",
              "start": 0,
              "username": "SalviaSWC"
            }
          ],
          "urls": [
            {
              "display_url": "pic.x.com/13v3fPqUWf",
              "end": 34,
              "expanded_url": "https://x.com/overdose_six/status/1975867821893812414/photo/1",
              "media_key": "3_1975867818555084800",
              "start": 11,
              "url": "https://t.co/13v3fPqUWf"
            }
          ]
        },
        "geo": {},
        "id": "1975867821893812414",
        "in_reply_to_user_id": "1659962043460354050",
        "lang": "qme",
        "note_tweet": {
          "entities": {}
        },
        "possibly_sensitive": false,
        "public_metrics": {
          "bookmark_count": 0,
          "impression_count": 14,
          "like_count": 1,
          "quote_count": 0,
          "reply_count": 1,
          "retweet_count": 0
        },
        "referenced_tweets": [
          {
            "id": "1975867044903133361",
            "type": "replied_to"
          }
        ],
        "reply_settings": "everyone",
        "text": "@SalviaSWC https://t.co/13v3fPqUWf"
      }
    ],
    "users": [
      {
        "created_at": "2023-05-20T16:39:35.000Z",
        "description": "07丨上海丨退役OIer丨虚无主义者丨\n非必要不键政🥺丨\nSay Know to Drugs 💊丨\n会发各种东西丨欢迎任何人🌈丨互fo🉑🥰丨如果没回fo的话，请私信哦",
        "entities": {
          "url": {
            "urls": [
              {
                "display_url": "github.com/SalviaSWC",
                "end": 23,
                "expanded_url": "https://github.com/SalviaSWC",
                "start": 0,
                "url": "https://t.co/NJRjXJi1ON"
              }
            ]
          }
        },
        "id": "1659962043460354050",
        "name": "鼠尾草～🌿",
        "profile_image_url": "https://pbs.twimg.com/profile_images/1886008586339282944/fBJFdCp0_normal.jpg",
        "protected": false,
        "public_metrics": {
          "followers_count": 1313,
          "following_count": 501,
          "like_count": 8255,
          "listed_count": 5,
          "media_count": 114,
          "tweet_count": 2698
        },
        "url": "https://t.co/NJRjXJi1ON",
        "username": "SalviaSWC",
        "verified": false
      },
      {
        "created_at": "2012-06-29T16:18:50.000Z",
        "description": "化学极乐百科:https://t.co/BlAoDIjZjK 提问箱:https://t.co/b5c8bbntR6 里推:@fuck_8964 药物代购可私信",
        "entities": {
          "description": {
            "mentions": [
              {
                "end": 72,
                "start": 62,
                "username": "fuck_8964"
              }
            ],
            "urls": [
              {
                "display_url": "overdose.day",
                "end": 30,
                "expanded_url": "http://overdose.day",
                "start": 7,
                "url": "https://t.co/BlAoDIjZjK"
              },
              {
                "display_url": "ngl.link/oder_six",
                "end": 58,
                "expanded_url": "https://ngl.link/oder_six",
                "start": 35,
                "url": "https://t.co/b5c8bbntR6"
              }
            ]
          },
          "url": {
            "urls": [
              {
                "display_url": "overdose.day",
                "end": 23,
                "expanded_url": "http://overdose.day",
                "start": 0,
                "url": "https://t.co/BlAoDIjZjK"
              }
            ]
          }
        },
        "id": "622036546",
        "location": "天国",
        "name": "椎名",
        "profile_image_url": "https://pbs.twimg.com/profile_images/1975218486835314688/8cF15QPg_normal.jpg",
        "protected": false,
        "public_metrics": {
          "followers_count": 1257,
          "following_count": 175,
          "like_count": 9816,
          "listed_count": 6,
          "media_count": 328,
          "tweet_count": 2737
        },
        "url": "https://t.co/BlAoDIjZjK",
        "username": "overdose_six",
        "verified": false
      }
    ]
  }
}