{
  "data": {
    "article": {},
    "attachments": {},
    "author_id": "1659962043460354050",
    "conversation_id": "1969204610481963171",
    "created_at": "2025-09-21T16:36:07.000Z",
    "edit_controls": {
      "editable_until": "2025-09-21T17:36:07.000Z",
      "edits_remaining": 5,
      "is_edit_eligible": false
    },
    "edit_history_tweet_ids": [
      "1969802833496342656"
    ],
    "entities": {
      "mentions": [
        {
          "end": 13,
          "id": "1811843582229381123",
          "start": 0,
          "username": "RainduRhinns"
        }
      ]
    },
    "geo": {},
    "id": "1969802833496342656",
    "in_reply_to_user_id": "1811843582229381123",
    "lang": "zh",
    "note_tweet": {
      "entities": {}
    },
    "possibly_sensitive": false,
    "public_metrics": {
      "bookmark_count": 0,
      "impression_count": 0,
      "like_count": 0,
      "quote_count": 0,
      "reply_count": 0,
      "retweet_count": 0
    },
    "referenced_tweets": [
      {
        "id": "1969802467400728681",
        "type": "replied_to"
      }
    ],
    "reply_settings": "everyone",
    "text": "@RainduRhinns 历史，单纯是没怎么学()"
  },
  "includes": {
    "tweets": [
      {
        "article": {},
        "attachments": {},
        "author_id": "1659962043460354050",
        "conversation_id": "1969204610481963171",
        "created_at": "2025-09-21T16:36:07.000Z",
        "edit_controls": {
          "editable_until": "2025-09-21T17:36:07.000Z",
          "edits_remaining": 5,
          "is_edit_eligible": false
        },
        "edit_history_tweet_ids": [
          "1969802833496342656"
        ],
        "entities": {
          "mentions": [
            {
              "end": 13,
              "id": "1811843582229381123",
              "start": 0,
              "username": "RainduRhinns"
            }
          ]
        },
        "geo": {},
        "id": "1969802833496342656",
        "in_reply_to_user_id": "1811843582229381123",
        "lang": "zh",
        "note_tweet": {
          "entities": {}
        },
        "possibly_sensitive": false,
        "public_metrics": {
          "bookmark_count": 0,
          "impression_count": 0,
          "like_count": 0,
          "quote_count": 0,
          "reply_count": 0,
          "retweet_count": 0
        },
        "referenced_tweets": [
          {
            "id": "1969802467400728681",
            "type": "replied_to"
          }
        ],
        "reply_settings": "everyone",
        "text": "@RainduRhinns 历史，单纯是没怎么学()"
      },
      {
        "article": {},
        "attachments": {},
        "author_id": "1811843582229381123",
        "conversation_id": "1969204610481963171",
        "created_at": "2025-09-21T16:34:40.000Z",
        "edit_controls": {
          "editable_until": "2025-09-21T17:34:40.000Z",
          "edits_remaining": 5,
          "is_edit_eligible": false
        },
        "edit_history_tweet_ids": [
          "1969802467400728681"
        ],
        "entities": {
          "mentions": [
            {
              "end": 10,
              "id": "1659962043460354050",
              "start": 0,
              "username": "SalviaSWC"
            }
          ]
        },
        "geo": {},
        "id": "1969802467400728681",
        "in_reply_to_user_id": "1659962043460354050",
        "lang": "zh",
        "note_tweet": {
          "entities": {}
        },
        "possibly_sensitive": false,
        "public_metrics": {
          "bookmark_count": 0,
          "impression_count": 2,
          "like_count": 1,
          "quote_count": 0,
          "reply_count": 1,
          "retweet_count": 0
        },
        "referenced_tweets": [
          {
            "id": "1969801332027781575",
            "type": "replied_to"
          }
        ],
        "reply_settings": "everyone",
        "text": "@SalviaSWC 数理化地史生国语英语里呢"
      }
    ],
    "users": [
      {
        "created_at": "2023-05-20T16:39:35.000Z",
        "description": "07丨上海丨退役OIer丨虚无主义者丨\n非必要不键政🥺丨\nSay Know to Drugs 💊丨\n会发各种东西丨欢迎任何人🌈丨互fo🉑🥰丨如果没回fo的话，请私信哦",
        "entities": {
          "url": {
            "urls": [
              {
                "display_url": "github.com/SalviaSWC",
                "end": 23,
                "expanded_url": "https://github.com/SalviaSWC",
                "start": 0,
                "url": "https://t.co/NJRjXJi1ON"
              }
            ]
          }
        },
        "id": "1659962043460354050",
        "name": "鼠尾草～🌿",
        "profile_image_url": "https://pbs.twimg.com/profile_images/1886008586339282944/fBJFdCp0_normal.jpg",
        "protected": false,
        "public_metrics": {
          "followers_count": 1252,
          "following_count": 483,
          "like_count": 7335,
          "listed_count": 0,
          "media_count": 106,
          "tweet_count": 2563
        },
        "url": "https://t.co/NJRjXJi1ON",
        "username": "SalviaSWC",
        "verified": false
      },
      {
        "created_at": "2024-07-12T19:22:45.000Z",
        "description": "NSFW 友跨 top 今天届到正太了吗bot 性压抑国男PhD 打HEMA和冷兵器兵击 兴趣是被砍 特长是砍人",
        "id": "1811843582229381123",
        "name": "Rhinnschneevall",
        "pinned_tweet_id": "1954924223811780638",
        "profile_image_url": "https://pbs.twimg.com/profile_images/1811850889470103552/M46HQocY_normal.jpg",
        "protected": false,
        "public_metrics": {
          "followers_count": 226,
          "following_count": 730,
          "like_count": 2866,
          "listed_count": 1,
          "media_count": 59,
          "tweet_count": 973
        },
        "username": "RainduRhinns",
        "verified": false
      }
    ]
  }
}