{
  "data": {
    "article": {},
    "attachments": {},
    "author_id": "1659962043460354050",
    "conversation_id": "2019820064074318044",
    "created_at": "2026-02-06T17:20:24.000Z",
    "edit_controls": {
      "editable_until": "2026-02-06T18:20:24.000Z",
      "edits_remaining": 5,
      "is_edit_eligible": false
    },
    "edit_history_tweet_ids": [
      "2019823503005122990"
    ],
    "entities": {
      "mentions": [
        {
          "end": 13,
          "id": "1866458229527764992",
          "start": 0,
          "username": "Citrus_amara"
        }
      ]
    },
    "geo": {},
    "id": "2019823503005122990",
    "in_reply_to_user_id": "1866458229527764992",
    "lang": "zh",
    "note_tweet": {
      "entities": {}
    },
    "possibly_sensitive": false,
    "public_metrics": {
      "bookmark_count": 0,
      "impression_count": 0,
      "like_count": 0,
      "quote_count": 0,
      "reply_count": 0,
      "retweet_count": 0
    },
    "referenced_tweets": [
      {
        "id": "2019820064074318044",
        "type": "replied_to"
      }
    ],
    "reply_settings": "everyone",
    "text": "@Citrus_amara 同意喵\n\n窝看到过哌甲酯比可卡因不容易成瘾的原因的猜想，其中一个原因就是这个(但是可能还有热力学成分"
  },
  "errors": [
    {
      "detail": "Sorry, you are not authorized to see the Tweet with referenced_tweets.id: [2019820064074318044].",
      "parameter": "referenced_tweets.id",
      "resource_id": "2019820064074318044",
      "resource_type": "tweet",
      "section": "includes",
      "title": "Authorization Error",
      "type": "https://api.twitter.com/2/problems/not-authorized-for-resource",
      "value": "2019820064074318044"
    }
  ],
  "includes": {
    "tweets": [
      {
        "article": {},
        "attachments": {},
        "author_id": "1659962043460354050",
        "conversation_id": "2019820064074318044",
        "created_at": "2026-02-06T17:20:24.000Z",
        "edit_controls": {
          "editable_until": "2026-02-06T18:20:24.000Z",
          "edits_remaining": 5,
          "is_edit_eligible": false
        },
        "edit_history_tweet_ids": [
          "2019823503005122990"
        ],
        "entities": {
          "mentions": [
            {
              "end": 13,
              "id": "1866458229527764992",
              "start": 0,
              "username": "Citrus_amara"
            }
          ]
        },
        "geo": {},
        "id": "2019823503005122990",
        "in_reply_to_user_id": "1866458229527764992",
        "lang": "zh",
        "note_tweet": {
          "entities": {}
        },
        "possibly_sensitive": false,
        "public_metrics": {
          "bookmark_count": 0,
          "impression_count": 0,
          "like_count": 0,
          "quote_count": 0,
          "reply_count": 0,
          "retweet_count": 0
        },
        "referenced_tweets": [
          {
            "id": "2019820064074318044",
            "type": "replied_to"
          }
        ],
        "reply_settings": "everyone",
        "text": "@Citrus_amara 同意喵\n\n窝看到过哌甲酯比可卡因不容易成瘾的原因的猜想，其中一个原因就是这个(但是可能还有热力学成分"
      }
    ],
    "users": [
      {
        "created_at": "2023-05-20T16:39:35.000Z",
        "description": "07丨上海丨退役OIer丨计算机💻丨虚无主义者🥺丨\n\n会发各种东西🎲丨非必要不键政🏳️丨不卖药🚫丨欢迎任何人🌈丨包容各种做法☮丨互fo🉑哦🥰如果没回fo的话，请私信哦📬丨\n\n脑婆:@DXM8964LXM\n\n丨Say Know to Drugs 💊丨知识无罪📚丨😼👍⬇请关注FreeODwiki喵",
        "entities": {
          "description": {
            "mentions": [
              {
                "end": 101,
                "start": 90,
                "username": "DXM8964LXM"
              }
            ]
          },
          "url": {
            "urls": [
              {
                "display_url": "github.com/SalviaSWC/Free…",
                "end": 23,
                "expanded_url": "https://github.com/SalviaSWC/FreeODwiki",
                "start": 0,
                "url": "https://t.co/ki2TerCSXa"
              }
            ]
          }
        },
        "id": "1659962043460354050",
        "name": "鼠尾草～🌿",
        "pinned_tweet_id": "2011996462771802282",
        "profile_image_url": "https://pbs.twimg.com/profile_images/2009567905659092992/cvZN-2cJ_normal.jpg",
        "protected": false,
        "public_metrics": {
          "followers_count": 2637,
          "following_count": 791,
          "like_count": 18608,
          "listed_count": 9,
          "media_count": 259,
          "tweet_count": 5246
        },
        "url": "https://t.co/ki2TerCSXa",
        "username": "SalviaSWC",
        "verified": false
      },
      {
        "created_at": "2024-12-10T12:21:43.000Z",
        "description": "多意识体。友顺跨女\nHRT：2025.8.28。\n妹妹 @shsh548866丨Astra｜主人@zqtlovekris99丨🐱@psych_angel_丨@mizuame19953",
        "entities": {
          "description": {
            "mentions": [
              {
                "end": 39,
                "start": 28,
                "username": "shsh548866"
              },
              {
                "end": 62,
                "start": 48,
                "username": "zqtlovekris99"
              },
              {
                "end": 77,
                "start": 64,
                "username": "psych_angel_"
              },
              {
                "end": 91,
                "start": 78,
                "username": "mizuame19953"
              }
            ]
          },
          "url": {
            "urls": [
              {
                "display_url": "ngl.link/citrus_amara",
                "end": 23,
                "expanded_url": "https://ngl.link/citrus_amara",
                "start": 0,
                "url": "https://t.co/dk3VYjAAy3"
              }
            ]
          }
        },
        "id": "1866458229527764992",
        "location": "地狱",
        "name": "🍊苦橙🍊8️⃣9️⃣6️⃣4️⃣",
        "pinned_tweet_id": "2008507094388142397",
        "profile_image_url": "https://pbs.twimg.com/profile_images/2010661981926170624/akXPsbou_normal.jpg",
        "protected": true,
        "public_metrics": {
          "followers_count": 1244,
          "following_count": 1003,
          "like_count": 16547,
          "listed_count": 6,
          "media_count": 331,
          "tweet_count": 8830
        },
        "url": "https://t.co/dk3VYjAAy3",
        "username": "Citrus_amara",
        "verified": false
      }
    ]
  }
}