{
  "data": {
    "article": {},
    "attachments": {
      "media_keys": [
        "3_2028673675688603648"
      ],
      "media_source_tweet_id": [
        "2028673677643092015"
      ]
    },
    "author_id": "1659962043460354050",
    "conversation_id": "2028684816279871612",
    "created_at": "2026-03-03T04:12:05.000Z",
    "edit_controls": {
      "editable_until": "2026-03-03T05:12:05.000Z",
      "edits_remaining": 5,
      "is_edit_eligible": false
    },
    "edit_history_tweet_ids": [
      "2028684816279871612"
    ],
    "entities": {
      "mentions": [
        {
          "end": 11,
          "id": "1327197298930028544",
          "start": 3,
          "username": "un_krvy"
        }
      ],
      "urls": [
        {
          "display_url": "pic.x.com/touGvg8vO8",
          "end": 40,
          "expanded_url": "https://x.com/un_krvy/status/2028673677643092015/photo/1",
          "media_key": "3_2028673675688603648",
          "start": 17,
          "url": "https://t.co/touGvg8vO8"
        }
      ]
    },
    "geo": {},
    "id": "2028684816279871612",
    "lang": "zh",
    "note_tweet": {
      "entities": {}
    },
    "possibly_sensitive": false,
    "public_metrics": {
      "bookmark_count": 0,
      "impression_count": 0,
      "like_count": 0,
      "quote_count": 0,
      "reply_count": 0,
      "retweet_count": 1
    },
    "referenced_tweets": [
      {
        "id": "2028673677643092015",
        "type": "retweeted"
      }
    ],
    "reply_settings": "everyone",
    "text": "RT @un_krvy: 最进步 https://t.co/touGvg8vO8"
  },
  "includes": {
    "media": [
      {
        "height": 1024,
        "media_key": "3_2028673675688603648",
        "public_metrics": {},
        "type": "photo",
        "url": "https://pbs.twimg.com/media/HCdL9aya8AAbN3N.jpg",
        "width": 472
      }
    ],
    "tweets": [
      {
        "article": {},
        "attachments": {
          "media_keys": [
            "3_2028673675688603648"
          ],
          "media_source_tweet_id": [
            "2028673677643092015"
          ]
        },
        "author_id": "1659962043460354050",
        "conversation_id": "2028684816279871612",
        "created_at": "2026-03-03T04:12:05.000Z",
        "edit_controls": {
          "editable_until": "2026-03-03T05:12:05.000Z",
          "edits_remaining": 5,
          "is_edit_eligible": false
        },
        "edit_history_tweet_ids": [
          "2028684816279871612"
        ],
        "entities": {
          "mentions": [
            {
              "end": 11,
              "id": "1327197298930028544",
              "start": 3,
              "username": "un_krvy"
            }
          ],
          "urls": [
            {
              "display_url": "pic.x.com/touGvg8vO8",
              "end": 40,
              "expanded_url": "https://x.com/un_krvy/status/2028673677643092015/photo/1",
              "media_key": "3_2028673675688603648",
              "start": 17,
              "url": "https://t.co/touGvg8vO8"
            }
          ]
        },
        "geo": {},
        "id": "2028684816279871612",
        "lang": "zh",
        "note_tweet": {
          "entities": {}
        },
        "possibly_sensitive": false,
        "public_metrics": {
          "bookmark_count": 0,
          "impression_count": 0,
          "like_count": 0,
          "quote_count": 0,
          "reply_count": 0,
          "retweet_count": 1
        },
        "referenced_tweets": [
          {
            "id": "2028673677643092015",
            "type": "retweeted"
          }
        ],
        "reply_settings": "everyone",
        "text": "RT @un_krvy: 最进步 https://t.co/touGvg8vO8"
      },
      {
        "article": {},
        "attachments": {
          "media_keys": [
            "3_2028673675688603648"
          ]
        },
        "author_id": "1327197298930028544",
        "conversation_id": "2028673677643092015",
        "created_at": "2026-03-03T03:27:50.000Z",
        "edit_controls": {
          "editable_until": "2026-03-03T04:27:50.000Z",
          "edits_remaining": 5,
          "is_edit_eligible": true
        },
        "edit_history_tweet_ids": [
          "2028673677643092015"
        ],
        "entities": {
          "urls": [
            {
              "display_url": "pic.x.com/touGvg8vO8",
              "end": 27,
              "expanded_url": "https://x.com/un_krvy/status/2028673677643092015/photo/1",
              "media_key": "3_2028673675688603648",
              "start": 4,
              "url": "https://t.co/touGvg8vO8"
            }
          ]
        },
        "geo": {},
        "id": "2028673677643092015",
        "lang": "zh",
        "note_tweet": {
          "entities": {}
        },
        "possibly_sensitive": false,
        "public_metrics": {
          "bookmark_count": 0,
          "impression_count": 71,
          "like_count": 3,
          "quote_count": 0,
          "reply_count": 0,
          "retweet_count": 1
        },
        "reply_settings": "everyone",
        "text": "最进步 https://t.co/touGvg8vO8"
      }
    ],
    "users": [
      {
        "created_at": "2023-05-20T16:39:35.000Z",
        "description": "07|上海|退役OIer|计算机💻|虚无主义者🥺|\n\n会发各种东西🎲|非必要不键政🏳️|不卖药🚫|欢迎任何人🌈|包容各种做法☮|互fo🉑哦🥰|没回fo的话，请私信我哦📬|\n\n脑婆:@DXM8964LXM\n\n|Say Know to Drugs 💊丨OD知识开源化|来FreeODwiki看看吧！",
        "entities": {
          "description": {
            "mentions": [
              {
                "end": 101,
                "start": 90,
                "username": "DXM8964LXM"
              }
            ]
          },
          "url": {
            "urls": [
              {
                "display_url": "freeodwiki.org",
                "end": 23,
                "expanded_url": "https://freeodwiki.org",
                "start": 0,
                "url": "https://t.co/20q0OtAeQd"
              }
            ]
          }
        },
        "id": "1659962043460354050",
        "name": "鼠尾草～🌿",
        "profile_image_url": "https://pbs.twimg.com/profile_images/2009567905659092992/cvZN-2cJ_normal.jpg",
        "protected": false,
        "public_metrics": {
          "followers_count": 2889,
          "following_count": 923,
          "like_count": 20340,
          "listed_count": 10,
          "media_count": 328,
          "tweet_count": 5873
        },
        "url": "https://t.co/20q0OtAeQd",
        "username": "SalviaSWC",
        "verified": false
      },
      {
        "created_at": "2020-11-13T10:31:21.000Z",
        "description": "https://t.co/sxGCC1hNAm 官方账号，专注于精神药物科普",
        "entities": {
          "description": {
            "urls": [
              {
                "display_url": "psydrugs.org",
                "end": 23,
                "expanded_url": "http://psydrugs.org",
                "start": 0,
                "url": "https://t.co/sxGCC1hNAm"
              }
            ]
          },
          "url": {
            "urls": [
              {
                "display_url": "psydrugs.org",
                "end": 23,
                "expanded_url": "http://psydrugs.org",
                "start": 0,
                "url": "https://t.co/sxGCC1hNAm"
              }
            ]
          }
        },
        "id": "1327197298930028544",
        "location": "Macragge",
        "name": "Psydrugs official by krvy #​心宿二",
        "pinned_tweet_id": "2027743850547339526",
        "profile_image_url": "https://pbs.twimg.com/profile_images/2015057185953263616/EoNq2pvq_normal.jpg",
        "protected": false,
        "public_metrics": {
          "followers_count": 1121,
          "following_count": 218,
          "like_count": 6211,
          "listed_count": 0,
          "media_count": 95,
          "tweet_count": 1240
        },
        "url": "https://t.co/sxGCC1hNAm",
        "username": "un_krvy",
        "verified": false
      }
    ]
  }
}