{
  "data": {
    "article": {},
    "attachments": {},
    "author_id": "1659962043460354050",
    "context_annotations": [
      {
        "domain": {
          "description": "Categories within Brand Verticals that narrow down the scope of Brands",
          "id": "46",
          "name": "Business Taxonomy"
        },
        "entity": {
          "description": "Brands, companies, advertisers and every non-person handle with the profit intent related to softwares, apps, communication equipments, hardwares",
          "id": "1557697333571112960",
          "name": "Technology Business"
        }
      },
      {
        "domain": {
          "description": "Entity Service top level domain, every item that is in Entity Service should be in this domain",
          "id": "30",
          "name": "Entities [Entity Service]"
        },
        "entity": {
          "description": "Technology and computing",
          "id": "848920371311001600",
          "name": "Technology"
        }
      },
      {
        "domain": {
          "description": "A grouping of interests and hobbies entities, like Novelty Food or Destinations",
          "id": "66",
          "name": "Interests and Hobbies Category"
        },
        "entity": {
          "description": "Computer programming",
          "id": "848921413196984320",
          "name": "Computer programming"
        }
      },
      {
        "domain": {
          "description": "A taxonomy of user interests. ",
          "id": "131",
          "name": "Unified Twitter Taxonomy"
        },
        "entity": {
          "description": "Computer programming",
          "id": "848921413196984320",
          "name": "Computer programming"
        }
      },
      {
        "domain": {
          "description": "Top level entities that describe a Brands industry",
          "id": "45",
          "name": "Brand Vertical"
        },
        "entity": {
          "id": "781974597226799105",
          "name": "B2B"
        }
      },
      {
        "domain": {
          "description": "Entity Service top level domain, every item that is in Entity Service should be in this domain",
          "id": "30",
          "name": "Entities [Entity Service]"
        },
        "entity": {
          "id": "781974597172203520",
          "name": "Services - B2B"
        }
      },
      {
        "domain": {
          "description": "Brands and Companies",
          "id": "47",
          "name": "Brand"
        },
        "entity": {
          "id": "10040692468",
          "name": "GitHub"
        }
      }
    ],
    "conversation_id": "2015972546144043159",
    "created_at": "2026-01-27T02:21:18.000Z",
    "edit_controls": {
      "editable_until": "2026-01-27T03:21:18.000Z",
      "edits_remaining": 5,
      "is_edit_eligible": false
    },
    "edit_history_tweet_ids": [
      "2015973357699903769"
    ],
    "entities": {
      "urls": [
        {
          "display_url": "x.com/i/grok?convers…",
          "end": 114,
          "expanded_url": "https://x.com/i/grok?conversation=2015802686768357728",
          "images": [
            {
              "height": 634,
              "url": "https://pbs.twimg.com/news_img/2013708984151351297/pzcvo9Lb?format=jpg&name=orig",
              "width": 1202
            },
            {
              "height": 150,
              "url": "https://pbs.twimg.com/news_img/2013708984151351297/pzcvo9Lb?format=jpg&name=150x150",
              "width": 150
            }
          ],
          "start": 91,
          "status": 200,
          "title": "X",
          "unwound_url": "https://x.com/i/flow/login",
          "url": "https://t.co/p6cz8NUaOo"
        }
      ]
    },
    "geo": {},
    "id": "2015973357699903769",
    "in_reply_to_user_id": "1659962043460354050",
    "lang": "zh",
    "note_tweet": {
      "entities": {}
    },
    "possibly_sensitive": false,
    "public_metrics": {
      "bookmark_count": 0,
      "impression_count": 0,
      "like_count": 1,
      "quote_count": 0,
      "reply_count": 0,
      "retweet_count": 0
    },
    "referenced_tweets": [
      {
        "id": "2015972546144043159",
        "type": "replied_to"
      }
    ],
    "reply_settings": "everyone",
    "text": "这里的“Free”的使用是开源项目的常见操作，主要表示自由软件。我以为大家看到FreeODwiki被放在github上面就会知道这一点呢......🥺\n\n看来还是得向大家解释一下阿\nhttps://t.co/p6cz8NUaOo"
  },
  "includes": {
    "tweets": [
      {
        "article": {},
        "attachments": {},
        "author_id": "1659962043460354050",
        "context_annotations": [
          {
            "domain": {
              "description": "Categories within Brand Verticals that narrow down the scope of Brands",
              "id": "46",
              "name": "Business Taxonomy"
            },
            "entity": {
              "description": "Brands, companies, advertisers and every non-person handle with the profit intent related to softwares, apps, communication equipments, hardwares",
              "id": "1557697333571112960",
              "name": "Technology Business"
            }
          },
          {
            "domain": {
              "description": "Entity Service top level domain, every item that is in Entity Service should be in this domain",
              "id": "30",
              "name": "Entities [Entity Service]"
            },
            "entity": {
              "description": "Technology and computing",
              "id": "848920371311001600",
              "name": "Technology"
            }
          },
          {
            "domain": {
              "description": "A grouping of interests and hobbies entities, like Novelty Food or Destinations",
              "id": "66",
              "name": "Interests and Hobbies Category"
            },
            "entity": {
              "description": "Computer programming",
              "id": "848921413196984320",
              "name": "Computer programming"
            }
          },
          {
            "domain": {
              "description": "A taxonomy of user interests. ",
              "id": "131",
              "name": "Unified Twitter Taxonomy"
            },
            "entity": {
              "description": "Computer programming",
              "id": "848921413196984320",
              "name": "Computer programming"
            }
          },
          {
            "domain": {
              "description": "Top level entities that describe a Brands industry",
              "id": "45",
              "name": "Brand Vertical"
            },
            "entity": {
              "id": "781974597226799105",
              "name": "B2B"
            }
          },
          {
            "domain": {
              "description": "Entity Service top level domain, every item that is in Entity Service should be in this domain",
              "id": "30",
              "name": "Entities [Entity Service]"
            },
            "entity": {
              "id": "781974597172203520",
              "name": "Services - B2B"
            }
          },
          {
            "domain": {
              "description": "Brands and Companies",
              "id": "47",
              "name": "Brand"
            },
            "entity": {
              "id": "10040692468",
              "name": "GitHub"
            }
          }
        ],
        "conversation_id": "2015972546144043159",
        "created_at": "2026-01-27T02:21:18.000Z",
        "edit_controls": {
          "editable_until": "2026-01-27T03:21:18.000Z",
          "edits_remaining": 5,
          "is_edit_eligible": false
        },
        "edit_history_tweet_ids": [
          "2015973357699903769"
        ],
        "entities": {
          "urls": [
            {
              "display_url": "x.com/i/grok?convers…",
              "end": 114,
              "expanded_url": "https://x.com/i/grok?conversation=2015802686768357728",
              "images": [
                {
                  "height": 634,
                  "url": "https://pbs.twimg.com/news_img/2013708984151351297/pzcvo9Lb?format=jpg&name=orig",
                  "width": 1202
                },
                {
                  "height": 150,
                  "url": "https://pbs.twimg.com/news_img/2013708984151351297/pzcvo9Lb?format=jpg&name=150x150",
                  "width": 150
                }
              ],
              "start": 91,
              "status": 200,
              "title": "X",
              "unwound_url": "https://x.com/i/flow/login",
              "url": "https://t.co/p6cz8NUaOo"
            }
          ]
        },
        "geo": {},
        "id": "2015973357699903769",
        "in_reply_to_user_id": "1659962043460354050",
        "lang": "zh",
        "note_tweet": {
          "entities": {}
        },
        "possibly_sensitive": false,
        "public_metrics": {
          "bookmark_count": 0,
          "impression_count": 0,
          "like_count": 1,
          "quote_count": 0,
          "reply_count": 0,
          "retweet_count": 0
        },
        "referenced_tweets": [
          {
            "id": "2015972546144043159",
            "type": "replied_to"
          }
        ],
        "reply_settings": "everyone",
        "text": "这里的“Free”的使用是开源项目的常见操作，主要表示自由软件。我以为大家看到FreeODwiki被放在github上面就会知道这一点呢......🥺\n\n看来还是得向大家解释一下阿\nhttps://t.co/p6cz8NUaOo"
      },
      {
        "article": {},
        "attachments": {},
        "author_id": "1659962043460354050",
        "conversation_id": "2015972546144043159",
        "created_at": "2026-01-27T02:18:04.000Z",
        "edit_controls": {
          "editable_until": "2026-01-27T03:18:04.000Z",
          "edits_remaining": 5,
          "is_edit_eligible": false
        },
        "edit_history_tweet_ids": [
          "2015972546144043159"
        ],
        "entities": {},
        "geo": {},
        "id": "2015972546144043159",
        "lang": "zh",
        "note_tweet": {
          "entities": {}
        },
        "possibly_sensitive": false,
        "public_metrics": {
          "bookmark_count": 0,
          "impression_count": 1,
          "like_count": 1,
          "quote_count": 0,
          "reply_count": 1,
          "retweet_count": 0
        },
        "reply_settings": "everyone",
        "text": "突然想起当时某人对我某贴子的回复，才发现了大家可能有一个重大误会⚠️：\n\nFreeODwiki名字中的“Free”不是说我们wiki主张“自由随意OD”，正确的理解是我们主张“OD的知识被公开的自由，和大家参与编写被公开的OD的知识的自由”\n\n我现在就有关事项做了澄清，很抱歉之前的误会。大家以后不要再理解错误了哦😢"
      }
    ],
    "users": [
      {
        "created_at": "2023-05-20T16:39:35.000Z",
        "description": "07丨上海丨退役OIer丨计算机💻丨虚无主义者🥺丨\n\n会发各种东西🎲丨非必要不键政🏳️丨不卖药🚫丨欢迎任何人🌈丨包容各种做法☮丨互fo🉑哦🥰如果没回fo的话，请私信哦📬丨\n\n脑婆:@DXM8964LXM\n\n丨Say Know to Drugs 💊丨知识无罪📚丨😼👍⬇请关注FreeODwiki喵",
        "entities": {
          "description": {
            "mentions": [
              {
                "end": 101,
                "start": 90,
                "username": "DXM8964LXM"
              }
            ]
          },
          "url": {
            "urls": [
              {
                "display_url": "github.com/SalviaSWC/Free…",
                "end": 23,
                "expanded_url": "https://github.com/SalviaSWC/FreeODwiki",
                "start": 0,
                "url": "https://t.co/ki2TerCSXa"
              }
            ]
          }
        },
        "id": "1659962043460354050",
        "name": "鼠尾草～🌿",
        "pinned_tweet_id": "2011996462771802282",
        "profile_image_url": "https://pbs.twimg.com/profile_images/2009567905659092992/cvZN-2cJ_normal.jpg",
        "protected": false,
        "public_metrics": {
          "followers_count": 2431,
          "following_count": 791,
          "like_count": 18363,
          "listed_count": 7,
          "media_count": 238,
          "tweet_count": 5095
        },
        "url": "https://t.co/ki2TerCSXa",
        "username": "SalviaSWC",
        "verified": false
      }
    ]
  }
}