{
  "data": {
    "article": {},
    "attachments": {},
    "author_id": "1659962043460354050",
    "conversation_id": "2042578667402887248",
    "created_at": "2026-04-10T12:21:18.000Z",
    "edit_controls": {
      "editable_until": "2026-04-10T13:21:18.000Z",
      "edits_remaining": 5,
      "is_edit_eligible": true
    },
    "edit_history_tweet_ids": [
      "2042578667402887248"
    ],
    "entities": {
      "urls": [
        {
          "display_url": "x.com/tankche8964/st…",
          "end": 157,
          "expanded_url": "https://twitter.com/tankche8964/status/2042570993122865586",
          "start": 134,
          "url": "https://t.co/ivD3wWGYqq"
        }
      ]
    },
    "geo": {},
    "id": "2042578667402887248",
    "lang": "zh",
    "note_tweet": {
      "entities": {}
    },
    "possibly_sensitive": false,
    "public_metrics": {
      "bookmark_count": 0,
      "impression_count": 0,
      "like_count": 0,
      "quote_count": 0,
      "reply_count": 0,
      "retweet_count": 0
    },
    "referenced_tweets": [
      {
        "id": "2042570993122865586",
        "type": "quoted"
      }
    ],
    "reply_settings": "everyone",
    "text": "“(一)”?\n\n意思是还会有23456是吧😯\n\n大家可以多多关注转发广州禁毒，也可以多多关注转发我们freeodwiki 哦👀\n\n他们更新他们的视频，我们更新我们关于OD的文档，共同进步嘛🤓☝\n\n他们这么积极地扩散OD，把OD推向风口浪尖，我们蹭个热度也是合理的吧🤔 https://t.co/ivD3wWGYqq"
  },
  "errors": [
    {
      "detail": "Could not find tweet with referenced_tweets.id: [2042570993122865586].",
      "parameter": "referenced_tweets.id",
      "resource_id": "2042570993122865586",
      "resource_type": "tweet",
      "title": "Not Found Error",
      "type": "https://api.twitter.com/2/problems/resource-not-found",
      "value": "2042570993122865586"
    }
  ],
  "includes": {
    "tweets": [
      {
        "article": {},
        "attachments": {},
        "author_id": "1659962043460354050",
        "conversation_id": "2042578667402887248",
        "created_at": "2026-04-10T12:21:18.000Z",
        "edit_controls": {
          "editable_until": "2026-04-10T13:21:18.000Z",
          "edits_remaining": 5,
          "is_edit_eligible": true
        },
        "edit_history_tweet_ids": [
          "2042578667402887248"
        ],
        "entities": {
          "urls": [
            {
              "display_url": "x.com/tankche8964/st…",
              "end": 157,
              "expanded_url": "https://twitter.com/tankche8964/status/2042570993122865586",
              "start": 134,
              "url": "https://t.co/ivD3wWGYqq"
            }
          ]
        },
        "geo": {},
        "id": "2042578667402887248",
        "lang": "zh",
        "note_tweet": {
          "entities": {}
        },
        "possibly_sensitive": false,
        "public_metrics": {
          "bookmark_count": 0,
          "impression_count": 0,
          "like_count": 0,
          "quote_count": 0,
          "reply_count": 0,
          "retweet_count": 0
        },
        "referenced_tweets": [
          {
            "id": "2042570993122865586",
            "type": "quoted"
          }
        ],
        "reply_settings": "everyone",
        "text": "“(一)”?\n\n意思是还会有23456是吧😯\n\n大家可以多多关注转发广州禁毒，也可以多多关注转发我们freeodwiki 哦👀\n\n他们更新他们的视频，我们更新我们关于OD的文档，共同进步嘛🤓☝\n\n他们这么积极地扩散OD，把OD推向风口浪尖，我们蹭个热度也是合理的吧🤔 https://t.co/ivD3wWGYqq"
      }
    ],
    "users": [
      {
        "created_at": "2023-05-20T16:39:35.000Z",
        "description": "07|上海|退役OIer|计算机💻|\n\n非必要不键政🏳️|不卖药🚫|欢迎任何人🌈|包容各种做法☮|互fo🉑哦🥰|没回fo的话，请私信我哦📬|\n\n脑婆:@DXM8964LXM\n\n丨药物知识开源化💊|来FreeODwiki看看吧！|Say Know to Drugs 😼",
        "entities": {
          "description": {
            "mentions": [
              {
                "end": 86,
                "start": 75,
                "username": "DXM8964LXM"
              }
            ]
          },
          "url": {
            "urls": [
              {
                "display_url": "freeodwiki.org",
                "end": 23,
                "expanded_url": "https://freeodwiki.org",
                "start": 0,
                "url": "https://t.co/20q0OtAMFL"
              }
            ]
          }
        },
        "id": "1659962043460354050",
        "name": "鼠尾草～🌿",
        "profile_image_url": "https://pbs.twimg.com/profile_images/2034583473692852224/nE4xPVUJ_normal.jpg",
        "protected": false,
        "public_metrics": {
          "followers_count": 3683,
          "following_count": 990,
          "like_count": 21970,
          "listed_count": 8,
          "media_count": 409,
          "tweet_count": 6670
        },
        "url": "https://t.co/20q0OtAMFL",
        "username": "SalviaSWC",
        "verified": false
      }
    ]
  }
}