{
  "data": {
    "article": {},
    "attachments": {},
    "author_id": "1659962043460354050",
    "conversation_id": "2022706622527680888",
    "created_at": "2026-02-15T03:19:21.000Z",
    "edit_controls": {
      "editable_until": "2026-02-15T04:19:21.000Z",
      "edits_remaining": 5,
      "is_edit_eligible": false
    },
    "edit_history_tweet_ids": [
      "2022873338247266743"
    ],
    "entities": {
      "mentions": [
        {
          "end": 15,
          "id": "1720356797758763008",
          "start": 0,
          "username": "huluobohaotang"
        }
      ]
    },
    "geo": {},
    "id": "2022873338247266743",
    "in_reply_to_user_id": "1720356797758763008",
    "lang": "zh",
    "note_tweet": {
      "entities": {}
    },
    "possibly_sensitive": false,
    "public_metrics": {
      "bookmark_count": 0,
      "impression_count": 0,
      "like_count": 0,
      "quote_count": 0,
      "reply_count": 0,
      "retweet_count": 0
    },
    "referenced_tweets": [
      {
        "id": "2022870305333743932",
        "type": "replied_to"
      }
    ],
    "reply_settings": "everyone",
    "text": "@huluobohaotang 吃完睡着不醒的概率远大于联用普瑞......\n\n不过里面有咖啡因，风险应该小一点"
  },
  "errors": [
    {
      "detail": "Sorry, you are not authorized to see the Tweet with referenced_tweets.id: [2022870305333743932].",
      "parameter": "referenced_tweets.id",
      "resource_id": "2022870305333743932",
      "resource_type": "tweet",
      "section": "includes",
      "title": "Authorization Error",
      "type": "https://api.twitter.com/2/problems/not-authorized-for-resource",
      "value": "2022870305333743932"
    }
  ],
  "includes": {
    "tweets": [
      {
        "article": {},
        "attachments": {},
        "author_id": "1659962043460354050",
        "conversation_id": "2022706622527680888",
        "created_at": "2026-02-15T03:19:21.000Z",
        "edit_controls": {
          "editable_until": "2026-02-15T04:19:21.000Z",
          "edits_remaining": 5,
          "is_edit_eligible": false
        },
        "edit_history_tweet_ids": [
          "2022873338247266743"
        ],
        "entities": {
          "mentions": [
            {
              "end": 15,
              "id": "1720356797758763008",
              "start": 0,
              "username": "huluobohaotang"
            }
          ]
        },
        "geo": {},
        "id": "2022873338247266743",
        "in_reply_to_user_id": "1720356797758763008",
        "lang": "zh",
        "note_tweet": {
          "entities": {}
        },
        "possibly_sensitive": false,
        "public_metrics": {
          "bookmark_count": 0,
          "impression_count": 0,
          "like_count": 0,
          "quote_count": 0,
          "reply_count": 0,
          "retweet_count": 0
        },
        "referenced_tweets": [
          {
            "id": "2022870305333743932",
            "type": "replied_to"
          }
        ],
        "reply_settings": "everyone",
        "text": "@huluobohaotang 吃完睡着不醒的概率远大于联用普瑞......\n\n不过里面有咖啡因，风险应该小一点"
      }
    ],
    "users": [
      {
        "created_at": "2023-05-20T16:39:35.000Z",
        "description": "07|上海|退役OIer|计算机💻|虚无主义者🥺|\n\n会发各种东西🎲|非必要不键政🏳️|不卖药🚫|欢迎任何人🌈|包容各种做法☮|互fo🉑哦🥰|没回fo的话，请私信我哦📬|\n\n脑婆:@DXM8964LXM\n\n丨Say Know to Drugs 💊丨OD知识开源化↓请支持FreeODwiki喵！",
        "entities": {
          "description": {
            "mentions": [
              {
                "end": 101,
                "start": 90,
                "username": "DXM8964LXM"
              }
            ]
          },
          "url": {
            "urls": [
              {
                "display_url": "github.com/SalviaSWC/Free…",
                "end": 23,
                "expanded_url": "https://github.com/SalviaSWC/FreeODwiki",
                "start": 0,
                "url": "https://t.co/ki2TerCl7C"
              }
            ]
          }
        },
        "id": "1659962043460354050",
        "location": "freeodwiki.org",
        "name": "鼠尾草～🌿",
        "pinned_tweet_id": "2011996462771802282",
        "profile_image_url": "https://pbs.twimg.com/profile_images/2009567905659092992/cvZN-2cJ_normal.jpg",
        "protected": false,
        "public_metrics": {
          "followers_count": 2692,
          "following_count": 797,
          "like_count": 18962,
          "listed_count": 10,
          "media_count": 278,
          "tweet_count": 5402
        },
        "url": "https://t.co/ki2TerCl7C",
        "username": "SalviaSWC",
        "verified": false
      },
      {
        "created_at": "2023-11-03T08:27:22.000Z",
        "description": "cat of 169🐱 05 Female PgdStu🎧🍟🍔🥤🚪1680JPY/C spl tri/EN/JP 😘🍩fobackAuto 山を伴って住み 水を宿して寝る 若い夢のような時間に乗じて、沿道の風景で生気を覚まして、今を生きて、生活を美しく潤しています",
        "id": "1720356797758763008",
        "location": "Coruscant",
        "name": "FoxAndTohTorrac🧊🍔🍟🍣🤤🇸🇪",
        "pinned_tweet_id": "1854448337673699556",
        "profile_image_url": "https://pbs.twimg.com/profile_images/1980716470414848001/A15vk27L_normal.jpg",
        "protected": true,
        "public_metrics": {
          "followers_count": 1315,
          "following_count": 4530,
          "like_count": 28280,
          "listed_count": 0,
          "media_count": 82,
          "tweet_count": 18250
        },
        "username": "huluobohaotang",
        "verified": false
      }
    ]
  }
}