{
  "data": {
    "article": {},
    "attachments": {},
    "author_id": "1659962043460354050",
    "conversation_id": "2067457629916389458",
    "created_at": "2026-06-18T04:01:25.000Z",
    "edit_controls": {
      "editable_until": "2026-06-18T05:01:25.000Z",
      "edits_remaining": 5,
      "is_edit_eligible": false
    },
    "edit_history_tweet_ids": [
      "2067457629916389458"
    ],
    "entities": {
      "mentions": [
        {
          "end": 15,
          "id": "1494669485214633984",
          "start": 3,
          "username": "Nu1tZ333216"
        }
      ]
    },
    "geo": {},
    "id": "2067457629916389458",
    "lang": "zh",
    "note_tweet": {
      "entities": {}
    },
    "possibly_sensitive": false,
    "public_metrics": {
      "bookmark_count": 0,
      "impression_count": 0,
      "like_count": 0,
      "quote_count": 0,
      "reply_count": 0,
      "retweet_count": 1
    },
    "referenced_tweets": [
      {
        "id": "2067292715520233609",
        "type": "retweeted"
      }
    ],
    "reply_settings": "everyone",
    "text": "RT @Nu1tZ333216: 拒绝使用药物并相信吃苦/“非药物疗法”优于药物治疗是智力低下的表现"
  },
  "includes": {
    "tweets": [
      {
        "article": {},
        "attachments": {},
        "author_id": "1659962043460354050",
        "conversation_id": "2067457629916389458",
        "created_at": "2026-06-18T04:01:25.000Z",
        "edit_controls": {
          "editable_until": "2026-06-18T05:01:25.000Z",
          "edits_remaining": 5,
          "is_edit_eligible": false
        },
        "edit_history_tweet_ids": [
          "2067457629916389458"
        ],
        "entities": {
          "mentions": [
            {
              "end": 15,
              "id": "1494669485214633984",
              "start": 3,
              "username": "Nu1tZ333216"
            }
          ]
        },
        "geo": {},
        "id": "2067457629916389458",
        "lang": "zh",
        "note_tweet": {
          "entities": {}
        },
        "possibly_sensitive": false,
        "public_metrics": {
          "bookmark_count": 0,
          "impression_count": 0,
          "like_count": 0,
          "quote_count": 0,
          "reply_count": 0,
          "retweet_count": 1
        },
        "referenced_tweets": [
          {
            "id": "2067292715520233609",
            "type": "retweeted"
          }
        ],
        "reply_settings": "everyone",
        "text": "RT @Nu1tZ333216: 拒绝使用药物并相信吃苦/“非药物疗法”优于药物治疗是智力低下的表现"
      },
      {
        "article": {},
        "attachments": {},
        "author_id": "1494669485214633984",
        "conversation_id": "2067292715520233609",
        "created_at": "2026-06-17T17:06:06.000Z",
        "edit_controls": {
          "editable_until": "2026-06-17T18:06:06.000Z",
          "edits_remaining": 5,
          "is_edit_eligible": true
        },
        "edit_history_tweet_ids": [
          "2067292715520233609"
        ],
        "entities": {
          "urls": [
            {
              "display_url": "x.com/TheB17w153/sta…",
              "end": 57,
              "expanded_url": "https://twitter.com/TheB17w153/status/2061074828648677583",
              "start": 34,
              "url": "https://t.co/WtsYYh7Uqd"
            }
          ]
        },
        "geo": {},
        "id": "2067292715520233609",
        "lang": "zh",
        "note_tweet": {
          "entities": {}
        },
        "possibly_sensitive": false,
        "public_metrics": {
          "bookmark_count": 0,
          "impression_count": 371,
          "like_count": 15,
          "quote_count": 0,
          "reply_count": 1,
          "retweet_count": 1
        },
        "referenced_tweets": [
          {
            "id": "2061074828648677583",
            "type": "quoted"
          }
        ],
        "reply_settings": "everyone",
        "text": "拒绝使用药物并相信吃苦/“非药物疗法”优于药物治疗是智力低下的表现 https://t.co/WtsYYh7Uqd"
      }
    ],
    "users": [
      {
        "created_at": "2023-05-20T16:39:35.000Z",
        "description": "非必要不键政🏳️|不卖药🚫|欢迎任何人🌈|包容各种做法☮|互fo🉑🥰|没回fo的话，请私信我哦📬|\n\n脑婆:@DXM8964LXM\n\n丨药物知识开源化💊|来FreeODwiki看看吧！https://t.co/ki2TerCl7C |Say Know to Drugs 😼",
        "entities": {
          "description": {
            "mentions": [
              {
                "end": 65,
                "start": 54,
                "username": "DXM8964LXM"
              }
            ],
            "urls": [
              {
                "display_url": "github.com/SalviaSWC/Free…",
                "end": 115,
                "expanded_url": "https://github.com/SalviaSWC/FreeODwiki",
                "start": 92,
                "url": "https://t.co/ki2TerCl7C"
              }
            ]
          },
          "url": {
            "urls": [
              {
                "display_url": "freeodwiki.org",
                "end": 23,
                "expanded_url": "https://freeodwiki.org",
                "start": 0,
                "url": "https://t.co/20q0OtAeQd"
              }
            ]
          }
        },
        "id": "1659962043460354050",
        "name": "鼠尾草～🌿",
        "profile_image_url": "https://pbs.twimg.com/profile_images/2034583473692852224/nE4xPVUJ_normal.jpg",
        "protected": false,
        "public_metrics": {
          "followers_count": 4859,
          "following_count": 1018,
          "like_count": 24599,
          "listed_count": 12,
          "media_count": 554,
          "tweet_count": 7921
        },
        "url": "https://t.co/20q0OtAeQd",
        "username": "SalviaSWC",
        "verified": false
      },
      {
        "created_at": "2022-02-18T13:45:58.000Z",
        "description": "=汐音  07 asd/adhd可能性微存？      航天/观鸟/音游 enby any pronoun 阴湿自闭地雷药蛆毒虫促智批 精神病弃疗者 混沌中立 已去键政化......                 \n夜鹭窝➡️https://t.co/SuFqJ2PRQa⬅️",
        "entities": {
          "description": {
            "urls": [
              {
                "display_url": "t.me/edgeshelter2",
                "end": 137,
                "expanded_url": "http://t.me/edgeshelter2",
                "start": 114,
                "url": "https://t.co/SuFqJ2PRQa"
              }
            ]
          }
        },
        "id": "1494669485214633984",
        "location": "0.9km",
        "name": "v10L3T",
        "pinned_tweet_id": "2058580985353265378",
        "profile_image_url": "https://pbs.twimg.com/profile_images/2013226822813581312/IlFzii36_normal.jpg",
        "protected": false,
        "public_metrics": {
          "followers_count": 727,
          "following_count": 1769,
          "like_count": 78911,
          "listed_count": 1,
          "media_count": 411,
          "tweet_count": 4972
        },
        "username": "Nu1tZ333216",
        "verified": false
      }
    ]
  }
}